axmath_client/__init__.py
axmath_client/client.py
axmath_client/exceptions.py
axmath_client/models.py
axmath_client/py.typed
axmath_client/mcp_server/__init__.py
axmath_client/mcp_server/__main__.py
axmath_client/mcp_server/server.py
axmath_client-1.0.1.dist-info/licenses/LICENSE
axmath_client-1.0.1.dist-info/METADATA
axmath_client-1.0.1.dist-info/WHEEL
axmath_client-1.0.1.dist-info/entry_points.txt
axmath_client-1.0.1.dist-info/top_level.txt
axmath_client-1.0.1.dist-info/RECORD
