Metadata-Version: 2.4
Name: axmath-client
Version: 1.0.1
Summary: Python client for AxMath theorem proving API - connects to private AxMath service
Author-email: Dirk Englund <englund@mit.edu>
Maintainer-email: Dirk Englund <englund@mit.edu>
License: MIT
Project-URL: Homepage, https://axmath.yourdomain.com
Project-URL: Documentation, https://axmath.yourdomain.com/docs
Project-URL: API Reference, https://axmath.yourdomain.com/api/docs
Project-URL: Bug Tracker, https://github.com/dirkenglund/math-physics-agents-dream-team/issues
Keywords: theorem-proving,lean4,mathematics,formal-verification,api-client
Classifier: Development Status :: 4 - Beta
Classifier: Intended Audience :: Science/Research
Classifier: Intended Audience :: Developers
Classifier: License :: OSI Approved :: MIT License
Classifier: Programming Language :: Python :: 3
Classifier: Programming Language :: Python :: 3.9
Classifier: Programming Language :: Python :: 3.10
Classifier: Programming Language :: Python :: 3.11
Classifier: Programming Language :: Python :: 3.12
Classifier: Programming Language :: Python :: 3.13
Classifier: Topic :: Scientific/Engineering :: Mathematics
Classifier: Topic :: Scientific/Engineering :: Artificial Intelligence
Classifier: Topic :: Software Development :: Libraries :: Python Modules
Requires-Python: >=3.9
License-File: LICENSE
Requires-Dist: httpx>=0.24.0
Requires-Dist: pydantic>=2.0.0
Provides-Extra: mcp
Requires-Dist: mcp>=0.1.0; extra == "mcp"
Provides-Extra: dev
Requires-Dist: pytest>=7.4.0; extra == "dev"
Requires-Dist: pytest-asyncio>=0.21.0; extra == "dev"
Requires-Dist: pytest-httpx>=0.21.0; extra == "dev"
Requires-Dist: black>=23.0.0; extra == "dev"
Requires-Dist: ruff>=0.1.0; extra == "dev"
Requires-Dist: mypy>=1.5.0; extra == "dev"
Dynamic: license-file
